loglicense/__init__.py
loglicense/__main__.py
loglicense/licenselogger.py
loglicense/utils.py
loglicense-0.1.8.dist-info/LICENSE
loglicense-0.1.8.dist-info/METADATA
loglicense-0.1.8.dist-info/WHEEL
loglicense-0.1.8.dist-info/entry_points.txt
loglicense-0.1.8.dist-info/RECORD
