Metadata-Version: 2.1
Name: loglicense
Version: 0.1.8
Summary: Log License
Home-page: https://github.com/martincjespersen/loglicense
License: Apache-2.0
Author: Martin Closter Jespersen
Author-email: martincjespersen@gmail.com
Requires-Python: >=3.8,<4.0
Classifier: Development Status :: 4 - Beta
Classifier: License :: OSI Approved :: Apache Software License
Classifier: Programming Language :: Python :: 3
Classifier: Programming Language :: Python :: 3.8
Classifier: Programming Language :: Python :: 3.9
Classifier: Programming Language :: Python :: 3.10
Classifier: Programming Language :: Python :: 3.11
Classifier: Topic :: Software Development
Classifier: Topic :: Software Development :: Documentation
Classifier: Topic :: Software Development :: Libraries
Classifier: Topic :: Software Development :: Libraries :: Python Modules
Classifier: Topic :: Software Development :: Quality Assurance
Classifier: Topic :: Text Processing :: Markup :: Markdown
Requires-Dist: certifi (>=2023.07.22,<2024.0.0)
Requires-Dist: gitpython (>=3.1.30,<4.0.0)
Requires-Dist: nox (>=2023.4.22,<2024.0.0)
Requires-Dist: nox-poetry (>=1.0.3,<2.0.0)
Requires-Dist: pathlib (>=1.0.1,<2.0.0)
Requires-Dist: tabulate (>=0.8.10,<0.9.0)
Requires-Dist: toml (>=0.10.2,<0.11.0)
Requires-Dist: tornado (>=6.3.2,<7.0.0)
Requires-Dist: typer (>=0.6.1,<0.7.0)
Requires-Dist: types-tabulate (>=0.8.11,<0.9.0)
Requires-Dist: types-toml (>=0.10.8,<0.11.0)
Project-URL: Changelog, https://github.com/martincjespersen/loglicense/releases
Project-URL: Documentation, https://loglicense.readthedocs.io
Project-URL: Repository, https://github.com/martincjespersen/loglicense
